terratorch_iterate/__init__.py
terratorch_iterate/backbone_benchmark.py
terratorch_iterate/benchmark_ray.py
terratorch_iterate/benchmark_types.py
terratorch_iterate/iterate2.py
terratorch_iterate/iterate_types.py
terratorch_iterate/main.py
terratorch_iterate/model_fitting.py
terratorch_iterate/module.py
terratorch_iterate/plot_tools.py
terratorch_iterate/py.typed
terratorch_iterate/repeat_best_experiment.py
terratorch_iterate/utils.py
terratorch_iterate/config_util/__init__.py
terratorch_iterate/config_util/build_iterate_config.py
terratorch_iterate/tests/__init__.py
terratorch_iterate-0.3.data/scripts/a_shell_script
terratorch_iterate-0.3.data/scripts/brief_salutation
terratorch_iterate-0.3.dist-info/licenses/LICENSE
terratorch_iterate-0.3.dist-info/METADATA
terratorch_iterate-0.3.dist-info/WHEEL
terratorch_iterate-0.3.dist-info/entry_points.txt
terratorch_iterate-0.3.dist-info/top_level.txt
terratorch_iterate-0.3.dist-info/RECORD
