Metadata-Version: 2.4
Name: terratorch-iterate
Version: 0.3
Summary: A terratorch's plugin for benchmarking and hyperparameter optimization
Author: Carlos Gomes, Daniela Szwarcman, Francesc Marti Escofet, Naomi Simumba, Paolo Fraccaro, Romeo Kienzler
Author-email: Leonardo Pondian Tizzei <ltizzei@br.ibm.com>
License: Apache License, Version 2.0
Project-URL: Homepage, https://github.com/terrastackai/iterate
Project-URL: Issues, https://github.com/terrastackai/iterate/issues
Classifier: Development Status :: 2 - Pre-Alpha
Classifier: Programming Language :: Python
Classifier: Programming Language :: Python :: 3.10
Classifier: Programming Language :: Python :: 3.11
Classifier: Programming Language :: Python :: 3.12
Classifier: Programming Language :: Python :: Implementation :: CPython
Requires-Python: >=3.11
License-File: LICENSE
Requires-Dist: terratorch>=1.1.0
Requires-Dist: requests>=2.32.0
Requires-Dist: Jinja2>=3.1.5
Requires-Dist: urllib3>=2.2.2
Requires-Dist: sqlparse>=0.5.0
Requires-Dist: scikit-learn>=1.5.0
Requires-Dist: pillow>=10.3.0
Requires-Dist: aiohttp>=3.9.4
Requires-Dist: tqdm>=4.66.3
Requires-Dist: werkzeug>=3.0.3
Requires-Dist: pytorch-lightning>=2.3.3
Requires-Dist: more-itertools
Requires-Dist: importlib-metadata
Requires-Dist: numpy
Requires-Dist: mlflow
Requires-Dist: optuna
Requires-Dist: types-tabulate
Requires-Dist: ray<=2.49.2
Requires-Dist: gputil
Requires-Dist: asyncio
Requires-Dist: opencv-python-headless
Requires-Dist: configspace
Requires-Dist: optuna-integration
Requires-Dist: psutil
Requires-Dist: tabulate>=0.9.0
Requires-Dist: torch
Requires-Dist: seaborn
Provides-Extra: dev
Requires-Dist: ruff; extra == "dev"
Requires-Dist: flake8; extra == "dev"
Requires-Dist: mkdocs-material; extra == "dev"
Requires-Dist: mkdocstrings[python]; extra == "dev"
Requires-Dist: mike; extra == "dev"
Requires-Dist: tox; extra == "dev"
Requires-Dist: pre-commit; extra == "dev"
Provides-Extra: test
Requires-Dist: coverage; extra == "test"
Requires-Dist: pytest; extra == "test"
Requires-Dist: pytest-cov; extra == "test"
Requires-Dist: deepdiff; extra == "test"
Provides-Extra: utility
Requires-Dist: geobench; extra == "utility"
Provides-Extra: nvidia
Requires-Dist: pynvml; extra == "nvidia"
Provides-Extra: amd
Requires-Dist: pyrsmi; extra == "amd"
Dynamic: license-file
